[
    {
        "id": 481,
        "name": "[COD] 1/2/3/4 seat Sofa Cover L-shaped Elastic Non-Slip Sofa Cover Removable And Washable",
        "img": "https://down-ph.img.susercontent.com/file/sg-11134201-22120-p1bjrnfrkzkv46_tn",
        "price": "₱69 - ₱339",
        "location": "Quezon City, Metro Manila",
        "sold_items": "6.8K sold",
        "category": "appliances"
    },
    {
        "id": 482,
        "name": "Aymar Super Thick Plain Color Chair Cover Stretch Elastic Dining Seat Cover Anti-Dirty",
        "img": "https://down-ph.img.susercontent.com/file/sg-11134201-23010-kjmk174ekrmv3b_tn",
        "price": "₱16 - ₱74",
        "location": "Quiapo, Metro Manila",
        "sold_items": "10K+ sold",
        "category": "appliances"
    },
    {
        "id": 483,
        "name": "2022 Punch free under table storage rack Cable management tray Desktop plug bracket Wire organizer Office appliances",
        "img": "https://down-ph.img.susercontent.com/file/sg-11134201-22100-q4187a5ioajvde_tn",
        "price": "₱549",
        "location": "Mainland China",
        "sold_items": "",
        "category": "appliances"
    },
    {
        "id": 484,
        "name": "[PH STOCK & COD] Elastic Plain Sofa Cover Regular & L Shape 1/2/3/4-seater Seat Cover Slipcover Set",
        "img": "https://down-ph.img.susercontent.com/file/b971c9d416919b534582edc6c770bac1_tn",
        "price": "₱76 - ₱379",
        "location": "Quezon City, Metro Manila",
        "sold_items": "10K+ sold",
        "category": "appliances"
    },
    {
        "id": 485,
        "name": "[COD] 1/2/3/4 seat Sofa Cover L-shaped Elastic Non-Slip Sofa Cover Removable And Washable",
        "img": "https://down-ph.img.susercontent.com/file/49469394ac41981b115cc2d5f588e4ec_tn",
        "price": "₱69 - ₱352",
        "location": "Quezon City, Metro Manila",
        "sold_items": "10K+ sold",
        "category": "appliances"
    },
    {
        "id": 486,
        "name": "⭐DHD⭐COD 3 Layer Stainless Steel Steamer And Cooker",
        "img": "https://down-ph.img.susercontent.com/file/183ea9ac178c94cf87f3bc9a6aef874a_tn",
        "price": "₱239",
        "location": "San Nicolas, Metro Manila",
        "sold_items": "10K+ sold",
        "category": "appliances"
    },
    {
        "id": 487,
        "name": "Waterproof Recliner Chair Covers For Armchairs Recliner Covers For Leather Chair Reclining Chair Covers Protect From Pets/kids Quil Ted With Non Slip Strap",
        "img": "https://down-ph.img.susercontent.com/file/078e99258948d13a6f9b8fe095a97488_tn",
        "price": "₱686 - ₱699",
        "location": "Mainland China",
        "sold_items": "398 sold",
        "category": "appliances"
    },
    {
        "id": 488,
        "name": "5 Pcs Corner Set Sofa Cover Stretchable Corner Seat Cover For Living Room Home Decoration Covers",
        "img": "https://down-ph.img.susercontent.com/file/sg-11134201-23010-l8jr95ceezlv2e_tn",
        "price": "₱1,449",
        "location": "Guiguinto, Bulacan",
        "sold_items": "664 sold",
        "category": "appliances"
    },
    {
        "id": 489,
        "name": "[PH STOCK & COD]3 in 1 Sofa Cover Set (3pcs) 2pcs Single and 1pc 2/3/4seater Set Sofa Cover",
        "img": "https://down-ph.img.susercontent.com/file/ph-11134207-7qul0-lippxeupdybqb8_tn",
        "price": "₱1,059 - ₱1,149",
        "location": "Sampaloc, Metro Manila",
        "sold_items": "1.5K sold",
        "category": "appliances"
    },
    {
        "id": 490,
        "name": "JEETEE Non Stick Pan 4Pcs Kitchen Cookware Set Original Light Weight Cooking Pot Kawali Wok Frying Pan/Casserole/Saucepan For Induction Cooker & Gas Stove",
        "img": "https://down-ph.img.susercontent.com/file/sg-11134201-23020-whm09ldru9mvd0_tn",
        "price": "₱2,599",
        "location": "San Pedro, Laguna",
        "sold_items": "576 sold",
        "category": "appliances"
    },
    {
        "id": 491,
        "name": "16/18 Inch Fan Dust-proof Protection Net Cover/ Electric Fan Safety Mesh Nets Cover/ Mesh Fan Guard Kids Finger Protector/ Summer Round Fan All-inclusive Filters",
        "img": "https://down-ph.img.susercontent.com/file/a4a62affe2879d737c7a2b7580d30d97_tn",
        "price": "₱53 - ₱55",
        "location": "Mainland China",
        "sold_items": "2.7K sold",
        "category": "appliances"
    },
    {
        "id": 492,
        "name": "4 Pieces/Set Recliner Sofa Cover for Living Room Elastic Reclining Chair Cover Protection Lazy Boy Relax Armchair Cover",
        "img": "https://down-ph.img.susercontent.com/file/sg-11134201-22100-e7i7zcz975hvd9_tn",
        "price": "₱650",
        "location": "Mainland China",
        "sold_items": "535 sold",
        "category": "appliances"
    },
    {
        "id": 493,
        "name": "100PCS Disposable Boot Shoes Covers Indoor Protect Home Floors Outdoors Water Resistant Cover-Z381",
        "img": "https://down-ph.img.susercontent.com/file/cbc74962bee0f43456a814c8f91b63b5_tn",
        "price": "₱54",
        "location": "Balagtas, Bulacan",
        "sold_items": "10K+ sold",
        "category": "appliances"
    },
    {
        "id": 494,
        "name": "Round Electric Fan Covers for Baby Kids Finger Protector Anti Dust Safety Mesh Net Cover Fan Guard",
        "img": "https://down-ph.img.susercontent.com/file/a1f654318554bf8abd8696a4b82ad55a_tn",
        "price": "₱29",
        "location": "Tondo I / Ii, Metro Manila",
        "sold_items": "10K+ sold",
        "category": "appliances"
    },
    {
        "id": 495,
        "name": "Solid Color Sofa Cover Set Armless Stretchable I Shape L Type Sala Set Cover Universal 1/2/3 Seater",
        "img": "https://down-ph.img.susercontent.com/file/d27b0651dba3ef955e2561dea9a10ef4_tn",
        "price": "₱89 - ₱439",
        "location": "Caloocan City, Metro Manila",
        "sold_items": "10K+ sold",
        "category": "appliances"
    },
    {
        "id": 496,
        "name": "1/2/3/4 Seater Seersucker Skirt Sofa Cover Stretch Sofa Protector Removable Slipcover Armchair Cover",
        "img": "https://down-ph.img.susercontent.com/file/cd88b5b820f808bcbc2b37417d96382f_tn",
        "price": "₱499 - ₱649",
        "location": "Marilao, Bulacan",
        "sold_items": "54 sold",
        "category": "appliances"
    },
    {
        "id": 497,
        "name": "Waterproof Office Swivel Chair Seat Cover Dining Room Chair Slipcover for Kitchen Banquet",
        "img": "https://down-ph.img.susercontent.com/file/sg-11134201-22100-daa7wg81weiv97_tn",
        "price": "₱89 - ₱150",
        "location": "San Nicolas, Metro Manila",
        "sold_items": "2.4K sold",
        "category": "appliances"
    },
    {
        "id": 498,
        "name": "Knitted Sofa Cover 1/2/3/4 Seater L Shape Universal Anti-Skid Stretch Couch Cover Sofa Protector",
        "img": "https://down-ph.img.susercontent.com/file/e83a35b419c49dc6d2c6fe7cebeceba0_tn",
        "price": "₱469 - ₱799",
        "location": "Marilao, Bulacan",
        "sold_items": "936 sold",
        "category": "appliances"
    },
    {
        "id": 499,
        "name": "1Pc Silicone Chair Leg Caps Feet Furniture Pads Table Covers Floor Protectors",
        "img": "https://down-ph.img.susercontent.com/file/af6d5621205b51f7544c9d27a6fc80a9_tn",
        "price": "₱9",
        "location": "Mainland China",
        "sold_items": "10K+ sold",
        "category": "appliances"
    },
    {
        "id": 500,
        "name": "Washing Machine Cover Waterproof Dustproof Thicken Sunscreen Protective Cover Top Open",
        "img": "https://down-ph.img.susercontent.com/file/2246f4e891d4b3781f7444b38110e98a_tn",
        "price": "₱159 - ₱199",
        "location": "Plaridel, Bulacan",
        "sold_items": "4.4K sold",
        "category": "appliances"
    },
    {
        "id": 501,
        "name": "[12 Color] 1 2 3 4 Seater Water Proof Sofa Slipcovers, Professional Non Slip Pet Sofa Protector",
        "img": "https://down-ph.img.susercontent.com/file/73e7f3d43063103c323dba1f0372fdad_tn",
        "price": "₱599 - ₱1,199",
        "location": "Valenzuela City, Metro Manila",
        "sold_items": "1.7K sold",
        "category": "appliances"
    },
    {
        "id": 502,
        "name": "Washing Machine Cover Waterproof Dustproof Sunblock Protective Cover Top Open S/M/L/XL Z11",
        "img": "https://down-ph.img.susercontent.com/file/ed551850a2b547c8397bfb659805a079_tn",
        "price": "₱214 - ₱249",
        "location": "Valenzuela City, Metro Manila",
        "sold_items": "10K+ sold",
        "category": "appliances"
    },
    {
        "id": 503,
        "name": "Sala Set L Shape Sofa Cover Set with Footstool Cover Free 2 Pcs Pillowcase Home Furniture Cover",
        "img": "https://down-ph.img.susercontent.com/file/a87477de0ff7c60c977e2b1054a5209c_tn",
        "price": "₱1,168",
        "location": "Guiguinto, Bulacan",
        "sold_items": "2K sold",
        "category": "appliances"
    },
    {
        "id": 504,
        "name": "Sheleep 3pcs Set Cover For Sofa 2pcs Single And 1pc 4 Seater Of Free Pillowcase",
        "img": "https://down-ph.img.susercontent.com/file/21ca6b8b2298b0cb1b11a7aaf99d109c_tn",
        "price": "₱1,229 - ₱1,237",
        "location": "Guiguinto, Bulacan",
        "sold_items": "594 sold",
        "category": "appliances"
    },
    {
        "id": 505,
        "name": "waterproof refrigerator dust proof cover",
        "img": "https://down-ph.img.susercontent.com/file/3d06cc016144fbf4b293de4e998451fd_tn",
        "price": "₱24 - ₱39",
        "location": "Valenzuela City, Metro Manila",
        "sold_items": "10K+ sold",
        "category": "appliances"
    },
    {
        "id": 506,
        "name": "DIY furniture chair leg cushion cover table leg non-slip mute rubber floor protector G_H",
        "img": "https://down-ph.img.susercontent.com/file/ph-11134201-23030-p0r44g6uqfov46_tn",
        "price": "₱5 - ₱9",
        "location": "Pasig City, Metro Manila",
        "sold_items": "10K+ sold",
        "category": "appliances"
    },
    {
        "id": 507,
        "name": "HOMEYOUNG Elastic Sofa Seat Cover Patchwork Cover CUSHION Seater SolidBack Cushion Stretchable",
        "img": "https://down-ph.img.susercontent.com/file/699d517730f6a9c0569049c0b59c84db_tn",
        "price": "₱119 - ₱439",
        "location": "Guiguinto, Bulacan",
        "sold_items": "10K+ sold",
        "category": "appliances"
    },
    {
        "id": 508,
        "name": "【FAST SHIPPING】1/2/3/4 Seater Sofa Cover Elastic Plain Sofa Cover Regular & L Shape Sofa Cover Set",
        "img": "https://down-ph.img.susercontent.com/file/8b06a561acea41b898082c083154e8cc_tn",
        "price": "₱149 - ₱499",
        "location": "Valenzuela City, Metro Manila",
        "sold_items": "1.2K sold",
        "category": "appliances"
    },
    {
        "id": 509,
        "name": "Stretch jacquard sofa cover 1/2/3/4 seat L-shaped universal sofa cover plain new fleece four seasons",
        "img": "https://down-ph.img.susercontent.com/file/sg-11134201-22120-b7q5bjxsq1kva9_tn",
        "price": "₱178 - ₱889",
        "location": "Marilao, Bulacan",
        "sold_items": "746 sold",
        "category": "appliances"
    },
    {
        "id": 510,
        "name": "S/M/L/XL Washing Machine Cover Waterproof Washer Dustproof Sunproof Case Furniture Protector",
        "img": "https://down-ph.img.susercontent.com/file/539509c1605e91639b3e60cf7960ad7e_tn",
        "price": "₱169 - ₱249",
        "location": "Marilao, Bulacan",
        "sold_items": "42 sold",
        "category": "appliances"
    },
    {
        "id": 511,
        "name": "【PH STOCK & COD] 1/2/3/4 Seater L Shape or Regular Shape Sofa Cover Plain Elastic Sofa Cover Set",
        "img": "https://down-ph.img.susercontent.com/file/839880dd0dba7a46a27c0f9a8273e6a1_tn",
        "price": "₱76 - ₱379",
        "location": "Marilao, Bulacan",
        "sold_items": "10K+ sold",
        "category": "appliances"
    },
    {
        "id": 512,
        "name": "Plastic Furniture Dust Cover Disposable Waterproof Car Dusty Bed Sofa Dust Proof Masking Film",
        "img": "https://down-ph.img.susercontent.com/file/ph-11134201-7qul5-lewvw32cqopg83_tn",
        "price": "₱35 - ₱79",
        "location": "Valenzuela City, Metro Manila",
        "sold_items": "1.5K sold",
        "category": "appliances"
    },
    {
        "id": 513,
        "name": "𝐏𝐑𝐈𝐍𝐓𝐄𝐑 𝐃𝐔𝐒𝐓 𝐂𝐎𝐕𝐄𝐑 protection from dust 𝗪𝗜𝗧𝗛 𝗜𝗡𝗞 𝗧𝗔𝗡𝗞",
        "img": "https://down-ph.img.susercontent.com/file/ph-11134207-7qukz-lgugcwuavlpca1_tn",
        "price": "₱150 - ₱220",
        "location": "Antipolo City, Rizal",
        "sold_items": "1.8K sold",
        "category": "appliances"
    },
    {
        "id": 514,
        "name": "Removable Computer Gaming Chair Covers Spandex Elastic Armchair Seat Cover for Home Office",
        "img": "https://down-ph.img.susercontent.com/file/ca1a6e1c0ccc49433753dba16674104f_tn",
        "price": "₱599",
        "location": "Mainland China",
        "sold_items": "1.9K sold",
        "category": "appliances"
    },
    {
        "id": 515,
        "name": "Stretch jacquard sofa cover 1/2/3/4 seat L-shaped universal sofa cover plain new fleece four seasons",
        "img": "https://down-ph.img.susercontent.com/file/2b41ba51edf0cc8a7b6c6511eea3331c_tn",
        "price": "₱371 - ₱898",
        "location": "Plaridel, Bulacan",
        "sold_items": "9.2K sold",
        "category": "appliances"
    },
    {
        "id": 516,
        "name": "Stretchy Chair Cover Slip covers Chair Protector, Washable Removable Dining Universal Fitting",
        "img": "https://down-ph.img.susercontent.com/file/0f8513423506e1c5813978decb51ebc6_tn",
        "price": "₱19 - ₱79",
        "location": "Guiguinto, Bulacan",
        "sold_items": "10K+ sold",
        "category": "appliances"
    },
    {
        "id": 517,
        "name": "Washing Machine Cover Waterproof Dustproof Case",
        "img": "https://down-ph.img.susercontent.com/file/2b8a65b6a85634ee17d4ba041cf3c73d_tn",
        "price": "₱67",
        "location": "Binondo, Metro Manila",
        "sold_items": "9K sold",
        "category": "appliances"
    },
    {
        "id": 518,
        "name": "❤NEW Thick Embossed velvet Sofa Covers Elastic Stretch Slipcovers Sofa Protector 1/2/3/4 seat",
        "img": "https://down-ph.img.susercontent.com/file/e15dd990f8fa8d12357eeaffb7e664a4_tn",
        "price": "₱235 - ₱743",
        "location": "Pulilan, Bulacan",
        "sold_items": "2.8K sold",
        "category": "appliances"
    },
    {
        "id": 519,
        "name": "【PH STOCK & High Quality] 1/2/3/4 Seater Sofa Cover Set Regular and L Shape Sofa Cover Stretchable",
        "img": "https://down-ph.img.susercontent.com/file/981368ba55c1c81b893f991dc85f0a95_tn",
        "price": "₱199 - ₱399",
        "location": "Sampaloc, Metro Manila",
        "sold_items": "10K+ sold",
        "category": "appliances"
    },
    {
        "id": 520,
        "name": "Anti pinch fan cover cartoon electric fan protective net 16-20 inch Fans Mesh Net for Finger Protect",
        "img": "https://down-ph.img.susercontent.com/file/b02f01aaaaff8568859fe7e37ceb608f_tn",
        "price": "₱19 - ₱49",
        "location": "Las Pinas City, Metro Manila",
        "sold_items": "10K+ sold",
        "category": "appliances"
    },
    {
        "id": 521,
        "name": "3 in 1 Sofa Cover Set Stretchable for 3 Seater and 2 Single Set 3 Pcs Seat Cover for Sofa",
        "img": "https://down-ph.img.susercontent.com/file/ph-11134207-7qul3-lg0rjmf97w4w17_tn",
        "price": "₱1,169 - ₱1,179",
        "location": "Guiguinto, Bulacan",
        "sold_items": "210 sold",
        "category": "appliances"
    },
    {
        "id": 522,
        "name": "DANSUNREVE Thicken Bed Head Cover All Inclusive Headboard Covers Elastic Back Protection Grey Cream Spandex Bedspread Bedside Case",
        "img": "https://down-ph.img.susercontent.com/file/1af887be481e6f5d2bc343ded9f48320_tn",
        "price": "₱418 - ₱688",
        "location": "Mainland China",
        "sold_items": "247 sold",
        "category": "appliances"
    },
    {
        "id": 523,
        "name": "[COD&PH Stcok] 2PC Chair Covers Removable Elastic Home Office Computer Split Chair Seat Protectors",
        "img": "https://down-ph.img.susercontent.com/file/cde8e43459131ffa32a6fa06b5328e2d_tn",
        "price": "₱39 - ₱129",
        "location": "Marilao, Bulacan",
        "sold_items": "1.2K sold",
        "category": "appliances"
    },
    {
        "id": 524,
        "name": "Fridge Dustproof Cover Refrigerator Top Cover with Kitchenware Organizer Pockets",
        "img": "https://down-ph.img.susercontent.com/file/dba61bb448eb197e77be18c7443d39f9_tn",
        "price": "₱24",
        "location": "Caloocan City, Metro Manila",
        "sold_items": "4.5K sold",
        "category": "appliances"
    },
    {
        "id": 525,
        "name": "washing machine cover Microwave Oven Refrigerator Waterproof dustproof Sunscreen cloth covers",
        "img": "https://down-ph.img.susercontent.com/file/de701fe480983f0b2a5916e7e1577357_tn",
        "price": "₱265",
        "location": "Valenzuela City, Metro Manila",
        "sold_items": "4.4K sold",
        "category": "appliances"
    },
    {
        "id": 526,
        "name": "Waterproof Jacquard Universal Dining Chair Seat Cover Stretchy Chair Cover For Dining Room",
        "img": "https://down-ph.img.susercontent.com/file/48f5092f4acefcf28415bb5803381ac7_tn",
        "price": "₱20 - ₱65",
        "location": "San Nicolas, Metro Manila",
        "sold_items": "10K+ sold",
        "category": "appliances"
    },
    {
        "id": 527,
        "name": "1/2/3-Seater Pet Dog Sofa Cover Chairs Couch Slipcover Mat Furniture Protector",
        "img": "https://down-ph.img.susercontent.com/file/sg-11134201-23020-t2conv59f2mvb5_tn",
        "price": "₱285 - ₱639",
        "location": "Marilao, Bulacan",
        "sold_items": "8.8K sold",
        "category": "appliances"
    },
    {
        "id": 528,
        "name": "\"(ALL POSITION) Replacement Cover for Uratex foam sofabed, Queen Size 60\"\"\"",
        "img": "https://down-ph.img.susercontent.com/file/08a371d463e3d25593fac1dc226fc06d_tn",
        "price": "₱871",
        "location": "Taytay, Rizal",
        "sold_items": "1.1K sold",
        "category": "appliances"
    },
    {
        "id": 529,
        "name": "[Spot] Waterproof, Dustproof And Sunscreen Protective Cover For Washing Machine Cover",
        "img": "https://down-ph.img.susercontent.com/file/sg-11134201-22110-cw2by0m9g8jvd7_tn",
        "price": "₱436 - ₱469",
        "location": "Bocaue, Bulacan",
        "sold_items": "602 sold",
        "category": "appliances"
    },
    {
        "id": 530,
        "name": "Angbon Waterproof Sunscreen Washing Machine Cover Dust Cover Top Load",
        "img": "https://down-ph.img.susercontent.com/file/1bf40285fcdabe6eae24885d494a96b2_tn",
        "price": "₱85",
        "location": "Las Pinas City, Metro Manila",
        "sold_items": "10K+ sold",
        "category": "appliances"
    },
    {
        "id": 531,
        "name": "【PH STOCK & COD] Sofa Cover Stretchable Plain Color Universal Armless 1/2/3 Seater L Shape Elastic",
        "img": "https://down-ph.img.susercontent.com/file/cfc5d18d741149d04652d7199d0d4b8d_tn",
        "price": "₱89 - ₱439",
        "location": "Caloocan City, Metro Manila",
        "sold_items": "5.5K sold",
        "category": "appliances"
    },
    {
        "id": 532,
        "name": "Refrigerator & Washing Machine Dust Proof Cover Storage Bag",
        "img": "https://down-ph.img.susercontent.com/file/ph-11134207-7qukz-lf9sznw5jwge83_tn",
        "price": "₱24 - ₱34",
        "location": "Tondo I / Ii, Metro Manila",
        "sold_items": "10K+ sold",
        "category": "appliances"
    },
    {
        "id": 533,
        "name": "\"Sihoo M56 Ergonomic Chair Seat Cover - \"\"COVER ONLY\"\"\"",
        "img": "https://down-ph.img.susercontent.com/file/sg-11134201-22110-1qtsxd26hikvb8_tn",
        "price": "₱350",
        "location": "Las Pinas City, Metro Manila",
        "sold_items": "169 sold",
        "category": "appliances"
    },
    {
        "id": 534,
        "name": "[COD] S/M/L Waterproof Chair Covers Elastic Computer Office Home Gaming Plaid Solid Color Removable",
        "img": "https://down-ph.img.susercontent.com/file/263682afd363509b34d0ad31379e2a38_tn",
        "price": "₱79 - ₱359",
        "location": "Marilao, Bulacan",
        "sold_items": "2.5K sold",
        "category": "appliances"
    },
    {
        "id": 535,
        "name": "Stretchy Chair Cover Slip covers Chair Protector, Washable Removable Dining Universal Fitting",
        "img": "https://down-ph.img.susercontent.com/file/cdd20f33223b8fff27c451271f07705d_tn",
        "price": "₱19 - ₱58",
        "location": "Quiapo, Metro Manila",
        "sold_items": "8.4K sold",
        "category": "appliances"
    },
    {
        "id": 536,
        "name": "Kitchen Winder Soft Cord Storage Organizer Appliances Cord Organizer office wire home wire cord orga",
        "img": "https://down-ph.img.susercontent.com/file/9f14806b96321fb115661d658114cbc2_tn",
        "price": "₱45",
        "location": "Tondo I / Ii, Metro Manila",
        "sold_items": "91 sold",
        "category": "appliances"
    },
    {
        "id": 537,
        "name": "[PH STOCK & COD] Thick Sofa Cover Jacquard Craft Regular L Shape Stretchable 1/2/3/4-seater",
        "img": "https://down-ph.img.susercontent.com/file/sg-11134201-23020-r15y8jb6vbnv05_tn",
        "price": "₱598 - ₱898",
        "location": "Quezon City, Metro Manila",
        "sold_items": "512 sold",
        "category": "appliances"
    },
    {
        "id": 538,
        "name": "NIDOUILLET Portable Electric Lunch Box Heating Double Layer Multifunctional Rice Cooker",
        "img": "https://down-ph.img.susercontent.com/file/sg-11134201-22120-56zadq5gelkv1c_tn",
        "price": "₱429 - ₱1,899",
        "location": "Trece Martires City, Cavite",
        "sold_items": "152 sold",
        "category": "appliances"
    },
    {
        "id": 539,
        "name": "【Free Pillowcase】3 in 1 Sofa Cover Set 2Pcs Single and 1Pc 3seater Set Sofa Cover Full Package Sofa Cover",
        "img": "https://down-ph.img.susercontent.com/file/ph-11134207-7qukw-li1c4kmrgetl2a_tn",
        "price": "₱995 - ₱999",
        "location": "Marilao, Bulacan",
        "sold_items": "463 sold",
        "category": "appliances"
    },
    {
        "id": 540,
        "name": "3 in 1 Sofa Cover Set 2 Single and 1 3seater Set Sofa Cover Full Package Sofa Cover（3pcs）",
        "img": "https://down-ph.img.susercontent.com/file/cf57609ff4c7435632443eaa024195a6_tn",
        "price": "₱999 - ₱1,199",
        "location": "Guiguinto, Bulacan",
        "sold_items": "10K+ sold",
        "category": "appliances"
    },
    {
        "id": 541,
        "name": "NIDOUILLET Portable Electric Lunch Box Heating Double Layer Multifunctional Rice Cooker",
        "img": "https://down-ph.img.susercontent.com/file/sg-11134201-22120-56zadq5gelkv1c_tn",
        "price": "₱429 - ₱1,899",
        "location": "Trece Martires City, Cavite",
        "sold_items": "152 sold",
        "category": "appliances"
    },
    {
        "id": 542,
        "name": "【Free Pillowcase】3 in 1 Sofa Cover Set 2Pcs Single and 1Pc 3seater Set Sofa Cover Full Package Sofa Cover",
        "img": "https://down-ph.img.susercontent.com/file/ph-11134207-7qukw-li1c4kmrgetl2a_tn",
        "price": "₱995 - ₱999",
        "location": "Marilao, Bulacan",
        "sold_items": "463 sold",
        "category": "appliances"
    },
    {
        "id": 543,
        "name": "3 in 1 Sofa Cover Set 2 Single and 1 3seater Set Sofa Cover Full Package Sofa Cover（3pcs）",
        "img": "https://down-ph.img.susercontent.com/file/cf57609ff4c7435632443eaa024195a6_tn",
        "price": "₱999 - ₱1,199",
        "location": "Guiguinto, Bulacan",
        "sold_items": "10K+ sold",
        "category": "appliances"
    },
    {
        "id": 544,
        "name": "Water Galon Cover Round Type Handwoven",
        "img": "https://down-ph.img.susercontent.com/file/402dd2abce4f2df2630fba25a1c5e2df_tn",
        "price": "₱350",
        "location": "Guihulngan City, Negros Oriental",
        "sold_items": "4.1K sold",
        "category": "appliances"
    },
    {
        "id": 545,
        "name": "[IAY] 15/17/19mm Pressure Cooker Handle Button Spiral Cover Explosion-proof Accessorie HKZ",
        "img": "https://down-ph.img.susercontent.com/file/sg-11134201-22120-b3frlf0kpclv9e_tn",
        "price": "₱69 - ₱80",
        "location": "Mainland China",
        "sold_items": "158 sold",
        "category": "appliances"
    },
    {
        "id": 546,
        "name": "Arthe.ph Printed Cover with Hole for Round 5 Gallon Water Jug (Bottle & Pump not included)",
        "img": "https://down-ph.img.susercontent.com/file/8ee3b79ec777267cf27381db8adb8070_tn",
        "price": "₱239 - ₱259",
        "location": "Pasig City, Metro Manila",
        "sold_items": "238 sold",
        "category": "appliances"
    },
    {
        "id": 547,
        "name": "【PH STOCK & COD] 1/2/3/4 Seater L Shape or Regular Shape Sofa Cover Plain Elastic Sofa Cover Set",
        "img": "https://down-ph.img.susercontent.com/file/80123e29686296614caf292b58579a44_tn",
        "price": "₱76 - ₱339",
        "location": "Marilao, Bulacan",
        "sold_items": "10K+ sold",
        "category": "appliances"
    },
    {
        "id": 548,
        "name": "Thick sofa protector Jacquard solid printed sofa covers living room couch cover corner L shape",
        "img": "https://down-ph.img.susercontent.com/file/dd98969f42a711685084714890537a3f_tn",
        "price": "₱399 - ₱999",
        "location": "Guiguinto, Bulacan",
        "sold_items": "2.1K sold",
        "category": "appliances"
    },
    {
        "id": 549,
        "name": "Toha Barbecue Multi-Function Skewer Cooker Electric Bbq Pan Kitchen Home Appliances",
        "img": "https://down-ph.img.susercontent.com/file/740f56707021a5e462572da45f2eadd5_tn",
        "price": "₱1,650",
        "location": "San Nicolas, Metro Manila",
        "sold_items": "35 sold",
        "category": "appliances"
    },
    {
        "id": 550,
        "name": "(3pcs）Sala Set Sofa Cover L Shape Sofa Cover with Footstool Cover Sofa Cover Set Free 2pcsPillowcase",
        "img": "https://down-ph.img.susercontent.com/file/sg-11134201-22100-afrnwokeylivf5_tn",
        "price": "₱1,159 - ₱1,169",
        "location": "Guiguinto, Bulacan",
        "sold_items": "607 sold",
        "category": "appliances"
    },
    {
        "id": 551,
        "name": "30*100cm High Viscosity Self Adhesive Leather Sofa Repair Subsidy Self Adhesive Stick on Sofa clothing Repairing Leather PU Fabric big Stickr Patches",
        "img": "https://down-ph.img.susercontent.com/file/86c002779feda2b13468cb2a85bf18b4_tn",
        "price": "₱67 - ₱202",
        "location": "Mainland China",
        "sold_items": "285 sold",
        "category": "appliances"
    },
    {
        "id": 552,
        "name": "S/M/L/XL Washing Machine Cover Waterproof Dustproof Sunproof Case Protector cover for washing machine automatic",
        "img": "https://down-ph.img.susercontent.com/file/a27df2ec1041d5da66b56075d04c3200_tn",
        "price": "₱148 - ₱218",
        "location": "San Pedro, Laguna",
        "sold_items": "1.3K sold",
        "category": "appliances"
    },
    {
        "id": 553,
        "name": "JHVN 2023 Christmas Chair Cover Stretch Elastic Dining Seat Cover Anti-Dirty Merry Christmas Gift",
        "img": "https://down-ph.img.susercontent.com/file/5bb1f7f580349773f05ab10c547a2d4a_tn",
        "price": "₱76 - ₱80",
        "location": "San Nicolas, Metro Manila",
        "sold_items": "10K+ sold",
        "category": "appliances"
    },
    {
        "id": 554,
        "name": "GPower Oxford Cloth Washing Machine Cover Waterproof Dustproof Top Open Protective Case",
        "img": "https://down-ph.img.susercontent.com/file/c46042cc56eac7b822fe72229fe2305f_tn",
        "price": "₱189 - ₱249",
        "location": "Las Pinas City, Metro Manila",
        "sold_items": "464 sold",
        "category": "appliances"
    },
    {
        "id": 555,
        "name": "EXTERNAL COVER of URATEX & other 3 CUTS FOAM SOFABED, protection cover for your original cover",
        "img": "https://down-ph.img.susercontent.com/file/88e261981a5205d6896fd1f2061fd4a1_tn",
        "price": "₱794 - ₱856",
        "location": "Taytay, Rizal",
        "sold_items": "487 sold",
        "category": "appliances"
    },
    {
        "id": 556,
        "name": "HOMEYOUNG Elastic Sofa Seat Cover Patchwork 1/2/3/4 Bench Solid back Cushion Stretchable",
        "img": "https://down-ph.img.susercontent.com/file/sg-11134201-22110-mjp238eo7pjvcd_tn",
        "price": "₱129 - ₱399",
        "location": "Guiguinto, Bulacan",
        "sold_items": "5.9K sold",
        "category": "appliances"
    },
    {
        "id": 557,
        "name": "[high quality]New Modern Elegant High Quality Fabric Elastic Knitted Dining Chair Cover Seat",
        "img": "https://down-ph.img.susercontent.com/file/af0fc4559d683ade49706780cf0dcbee_tn",
        "price": "₱220 - ₱225",
        "location": "Plaridel, Bulacan",
        "sold_items": "1.3K sold",
        "category": "appliances"
    },
    {
        "id": 558,
        "name": "24cm/26cm/28cm Non-stick Diamond Frying Pan Kitchen Iron Frying Pan for Gas Stove，induction Cooker",
        "img": "https://down-ph.img.susercontent.com/file/ph-11134207-7qul5-lhuaps5x1gx304_tn",
        "price": "₱88 - ₱254",
        "location": "General Trias, Cavite",
        "sold_items": "5K sold",
        "category": "appliances"
    },
    {
        "id": 559,
        "name": "【PH Stock】Stretchy Chair Cover Slip covers Chair Protector,Plain Cover ng upuan Universal HOMEYOUNG",
        "img": "https://down-ph.img.susercontent.com/file/7352a93d6dc3cd954530768116fd4a2d_tn",
        "price": "₱59",
        "location": "Guiguinto, Bulacan",
        "sold_items": "10K+ sold",
        "category": "appliances"
    },
    {
        "id": 560,
        "name": "Cozylife Wing Back Arm Chair Cover 2-Piece Wingback Sofa Slipcover",
        "img": "https://down-ph.img.susercontent.com/file/626ea9ea7e5683bcd2a392388148077a_tn",
        "price": "₱980 - ₱1,328",
        "location": "Mainland China",
        "sold_items": "147 sold",
        "category": "appliances"
    },
    {
        "id": 561,
        "name": "[Spot] Waterproof, dustproof and sunscreen protective cover for washing machine cover",
        "img": "https://down-ph.img.susercontent.com/file/c085ad84211c0f6608420014b2af24b5_tn",
        "price": "₱430 - ₱469",
        "location": "Plaridel, Bulacan",
        "sold_items": "2.4K sold",
        "category": "appliances"
    },
    {
        "id": 562,
        "name": "Waterproof Sofa Cover Set Cushion Cover Anti-slip Pet Dog Sofa Cover Couch Mat Sofa Protect",
        "img": "https://down-ph.img.susercontent.com/file/ph-11134207-7qukx-lh4jru22taeeec_tn",
        "price": "₱289 - ₱529",
        "location": "Guiguinto, Bulacan",
        "sold_items": "2.2K sold",
        "category": "appliances"
    },
    {
        "id": 563,
        "name": "A(2 and 1)Swivel chair cover retractable removable computer office washable swivel lift chair cover",
        "img": "https://down-ph.img.susercontent.com/file/3128bf12691115dab1e7ea8a69db2a73_tn",
        "price": "₱99 - ₱119",
        "location": "Plaridel, Bulacan",
        "sold_items": "4.9K sold",
        "category": "appliances"
    },
    {
        "id": 564,
        "name": "Front Open Zippered Washing Machine Cover Dust Free Waterproof Laundry Supplies",
        "img": "https://down-ph.img.susercontent.com/file/ae058d7587dba10cd2be1b022c7b58a5_tn",
        "price": "₱381",
        "location": "Mainland China",
        "sold_items": "734 sold",
        "category": "appliances"
    },
    {
        "id": 565,
        "name": "【PH STOCK & COD] 1/2/3/4 Seater L Shape or Regular Shape Sofa Cover Plain Elastic Sofa Cover Set",
        "img": "https://down-ph.img.susercontent.com/file/1a7e713469b2622e047813ace67e246e_tn",
        "price": "₱76 - ₱339",
        "location": "Marilao, Bulacan",
        "sold_items": "10K+ sold",
        "category": "appliances"
    },
    {
        "id": 566,
        "name": "(ALL POSITION) Replacement Cover for uratex foam sofabed, FAMILY Size 54''",
        "img": "https://down-ph.img.susercontent.com/file/c0cfda1b5750e9dff356fba63653effb_tn",
        "price": "₱852",
        "location": "Taytay, Rizal",
        "sold_items": "518 sold",
        "category": "appliances"
    },
    {
        "id": 567,
        "name": "Universal Thick Embossed velvet Sofa Covers Elastic Stretch Slipcovers Sofa Protector 1/2/3/4 seat",
        "img": "https://down-ph.img.susercontent.com/file/4a9a1aa1e42e0963dc1aeb72dd333da2_tn",
        "price": "₱411 - ₱898",
        "location": "Plaridel, Bulacan",
        "sold_items": "10K+ sold",
        "category": "appliances"
    },
    {
        "id": 568,
        "name": "（3pcs）3 in 1 Sofa Cover Set 2pcs Single and 1pc 3seater Set Sofa Cover Full Package Sofa Cover",
        "img": "https://down-ph.img.susercontent.com/file/ph-11134201-7qukw-leqxwaqivhbdd6_tn",
        "price": "₱719 - ₱1,099",
        "location": "Marilao, Bulacan",
        "sold_items": "445 sold",
        "category": "appliances"
    },
    {
        "id": 569,
        "name": "MINIMALIST NEUTRAL Plain Water Container Cover",
        "img": "https://down-ph.img.susercontent.com/file/ph-11134207-7qul2-lglqzdgyf6gob1_tn",
        "price": "₱90",
        "location": "Mexico, Pampanga",
        "sold_items": "1.2K sold",
        "category": "appliances"
    },
    {
        "id": 570,
        "name": "Large Round Back Cushion Integrated Chair Cover Negotiation Dining Elastic Household Universal Arc Stool Chair Cover",
        "img": "https://down-ph.img.susercontent.com/file/7dd50a08f2dd1fcdea327980f1265244_tn",
        "price": "₱296 - ₱592",
        "location": "Mainland China",
        "sold_items": "1.2K sold",
        "category": "appliances"
    },
    {
        "id": 571,
        "name": "Fitted Cleopatra Sofa Cover Long Sofa Cover Cleopatra Cover Stretchable Cover for Cleopatra Sofa Set",
        "img": "https://down-ph.img.susercontent.com/file/9d54dcd14d44e7189a07d9c977db1cc5_tn",
        "price": "₱499 - ₱599",
        "location": "Guiguinto, Bulacan",
        "sold_items": "1.5K sold",
        "category": "appliances"
    },
    {
        "id": 572,
        "name": "Sheleep Plain Color Sofa Cover 1/2/3/4 Seater Regular or L Shape Sofa Cover Stretchable Sofa Cover",
        "img": "https://down-ph.img.susercontent.com/file/1b615a97a5e7562effc18e002ee76a12_tn",
        "price": "₱259 - ₱599",
        "location": "Guiguinto, Bulacan",
        "sold_items": "3.6K sold",
        "category": "appliances"
    },
    {
        "id": 573,
        "name": "4fold sofa bed cover (cover only)",
        "img": "https://down-ph.img.susercontent.com/file/5ff079d5612f6ef3f05608c6103cc904_tn",
        "price": "₱650 - ₱880",
        "location": "Victorias City, Negros Occidental",
        "sold_items": "215 sold",
        "category": "appliances"
    },
    {
        "id": 574,
        "name": "【PH Stock】Sofa cushion Seat Cover 1/2/3/ Seater cushion slipcover square cushion Sofa Seat Cushion",
        "img": "https://down-ph.img.susercontent.com/file/334c641a655639dedb273457f9258a13_tn",
        "price": "₱119 - ₱399",
        "location": "Guiguinto, Bulacan",
        "sold_items": "8.2K sold",
        "category": "appliances"
    },
    {
        "id": 575,
        "name": "Waterproof Washing Machine Cover Dust Cover Protective Case",
        "img": "https://down-ph.img.susercontent.com/file/9932f2a6f3576f09519bd67eaf95a6f0_tn",
        "price": "₱68",
        "location": "Valenzuela City, Metro Manila",
        "sold_items": "10K+ sold",
        "category": "appliances"
    },
    {
        "id": 576,
        "name": "Waterproof Washing Machine Cover Protective Case Dust Cover",
        "img": "https://down-ph.img.susercontent.com/file/9932f2a6f3576f09519bd67eaf95a6f0_tn",
        "price": "₱75",
        "location": "Valenzuela City, Metro Manila",
        "sold_items": "10K+ sold",
        "category": "appliances"
    },
    {
        "id": 577,
        "name": "Office Chair Cover Spandex Office Seat Cover Elastic Armchair Computer Chair Slipcover",
        "img": "https://down-ph.img.susercontent.com/file/6d737733e6659951fd0cef096a5cad32_tn",
        "price": "₱219 - ₱269",
        "location": "Marilao, Bulacan",
        "sold_items": "3.4K sold",
        "category": "appliances"
    },
    {
        "id": 578,
        "name": "Reusable Home Dust Proof Elastic Furniture Water Dispenser Cover",
        "img": "https://down-ph.img.susercontent.com/file/52a58fee524b97a0640c9257ed80bfdd_tn",
        "price": "₱166 - ₱172",
        "location": "Mainland China",
        "sold_items": "1K sold",
        "category": "appliances"
    },
    {
        "id": 579,
        "name": "【Gift】 2.2L Large Capactiy Portable Electric Heating Cooking Lunch Box Multifunctional Rice Cooker",
        "img": "https://down-ph.img.susercontent.com/file/sg-11134201-22090-tqt90xhrd4hv09_tn",
        "price": "₱488 - ₱588",
        "location": "Marilao, Bulacan",
        "sold_items": "1.5K sold",
        "category": "appliances"
    },
    {
        "id": 580,
        "name": "Kitchen Shelf Gas Stove Bench 110*40*80CM Kitchen Organizer Home Kitchen Storage Rack",
        "img": "https://down-ph.img.susercontent.com/file/ph-11134207-7r98o-lkuquhnuxhdsec_tn",
        "price": "₱1,088 - ₱1,988",
        "location": "Taytay, Rizal",
        "sold_items": "1.8K sold",
        "category": "appliances"
    },
    {
        "id": 581,
        "name": "New Rubber Pads Leg Cap Feet Cover Floor Protector For Home Furniture Chair Table",
        "img": "https://down-ph.img.susercontent.com/file/bef0d1299d88ddd79e95bd3d3e5037c9_tn",
        "price": "₱27",
        "location": "Santa Cruz, Metro Manila",
        "sold_items": "5.6K sold",
        "category": "appliances"
    },
    {
        "id": 582,
        "name": "Curved Chair Cover Universal Elasticity Universal Chair Back Cover Triangle Dining Chair Cover Simple Modern Nordic",
        "img": "https://down-ph.img.susercontent.com/file/5348aa46dd615fb05b0935ed3b813425_tn",
        "price": "₱289",
        "location": "Mainland China",
        "sold_items": "421 sold",
        "category": "appliances"
    },
    {
        "id": 583,
        "name": "#Ready Stock to Ship# 1/2/3/4 Seater Sofa Cover L-Shape Elastic Sofa Protector Couch Slipcover",
        "img": "https://down-ph.img.susercontent.com/file/3340928e871f36287309aa904ed20691_tn",
        "price": "₱249 - ₱379",
        "location": "Marilao, Bulacan",
        "sold_items": "3.4K sold",
        "category": "appliances"
    },
    {
        "id": 584,
        "name": "[INS latest fabric + exclusive] Elastic sofa cover with skirt Universal sofa cover with lace skirt",
        "img": "https://down-ph.img.susercontent.com/file/8a0a99d64d8b4319726a8503037959b5_tn",
        "price": "₱244 - ₱910",
        "location": "Plaridel, Bulacan",
        "sold_items": "1.2K sold",
        "category": "appliances"
    },
    {
        "id": 585,
        "name": "Set of 3 Couch Coat Reversible Washable Sofa Cover (Brown)",
        "img": "https://down-ph.img.susercontent.com/file/4e39894ddc0b9556849f1d4afbff6014_tn",
        "price": "₱128 - ₱488",
        "location": "Binondo, Metro Manila",
        "sold_items": "331 sold",
        "category": "appliances"
    },
    {
        "id": 586,
        "name": "Sheleep Sofa Cover Set of 3pcs 2 single and 1 3seater Set Sofa Cover Free 3pcs pillowcase 3in1 Cover",
        "img": "https://down-ph.img.susercontent.com/file/ph-11134201-23020-f3etlh7qymnvd4_tn",
        "price": "₱999 - ₱1,199",
        "location": "Guiguinto, Bulacan",
        "sold_items": "520 sold",
        "category": "appliances"
    },
    {
        "id": 587,
        "name": "Refrigerator & Washing Machine Dust Proof Cover Storage Bag",
        "img": "https://down-ph.img.susercontent.com/file/14d952298e3692c048097ea1c790166f_tn",
        "price": "₱30",
        "location": "Quezon City, Metro Manila",
        "sold_items": "10K+ sold",
        "category": "appliances"
    },
    {
        "id": 588,
        "name": "Pink Elegance Chair Cover Stretch Elastic Dining Seat",
        "img": "https://down-ph.img.susercontent.com/file/c80d9b740167fc6177bcab6737010afa_tn",
        "price": "₱29 - ₱59",
        "location": "Pasay City, Metro Manila",
        "sold_items": "10K+ sold",
        "category": "appliances"
    },
    {
        "id": 589,
        "name": "【High Quality & COD] 1/2/3/4 Seater Sofa Cover Set Regular Shape L Shape Sofa Cover Stretchable",
        "img": "https://down-ph.img.susercontent.com/file/ph-11134201-7qula-lev8bzycqbdaf6_tn",
        "price": "₱199 - ₱389",
        "location": "Sampaloc, Metro Manila",
        "sold_items": "10K+ sold",
        "category": "appliances"
    },
    {
        "id": 590,
        "name": "[PH STOCK&COD] 1/2/3/4-seater Seat Cover Slipcover Elastic Sofa Cover Regular &L Shape Stretchable",
        "img": "https://down-ph.img.susercontent.com/file/573738d2b152cc9327e2b855ade13348_tn",
        "price": "₱49 - ₱379",
        "location": "Marilao, Bulacan",
        "sold_items": "6.7K sold",
        "category": "appliances"
    },
    {
        "id": 591,
        "name": "【Local sellers +COD】6 Sizes Outdoor AC Air Conditioner Cover Dustproof Waterproof Sunproof Protector",
        "img": "https://down-ph.img.susercontent.com/file/1fd80ac22e07405164b132ce12c39143_tn",
        "price": "₱158 - ₱550",
        "location": "Valenzuela City, Metro Manila",
        "sold_items": "464 sold",
        "category": "appliances"
    },
    {
        "id": 592,
        "name": "The Best Bosui Washing Machine Cover ,Waterproof w/ Lining",
        "img": "https://down-ph.img.susercontent.com/file/ph-11134207-7qul2-lfq0t9flznckba_tn",
        "price": "₱450 - ₱700",
        "location": "Santa Maria, Bulacan",
        "sold_items": "385 sold",
        "category": "appliances"
    },
    {
        "id": 593,
        "name": "Fullpace Helmet Cover Character Material",
        "img": "https://down-ph.img.susercontent.com/file/83e62a05b96ed55312a5008685b6b6e5_tn",
        "price": "₱196",
        "location": "Indonesia",
        "sold_items": "1.4K sold",
        "category": "appliances"
    },
    {
        "id": 594,
        "name": "Ref Cover with pocket",
        "img": "https://down-ph.img.susercontent.com/file/sg-11134201-22100-i6gj620gqdiva1_tn",
        "price": "₱109 - ₱115",
        "location": "San Luis, Pampanga",
        "sold_items": "10K+ sold",
        "category": "appliances"
    },
    {
        "id": 595,
        "name": "Round Water Container Dust Cover",
        "img": "https://down-ph.img.susercontent.com/file/e3b8554253b601f0bb6ba2971c9c5914_tn",
        "price": "₱179",
        "location": "Guiguinto, Bulacan",
        "sold_items": "2.5K sold",
        "category": "appliances"
    },
    {
        "id": 596,
        "name": "【NEW 2023 Exclusive】1/2/3/4 Seat Universal Sofa Cover Anti-Slip Living Room Sofa Cover Set For L Sha",
        "img": "https://down-ph.img.susercontent.com/file/ad4deb30007bc86881e6ac945f796c14_tn",
        "price": "₱241 - ₱910",
        "location": "Plaridel, Bulacan",
        "sold_items": "5.5K sold",
        "category": "appliances"
    },
    {
        "id": 597,
        "name": "1/2/3/4 Seater Sofa Covers High Stretch L-Shaped Corn Fleece Cover",
        "img": "https://down-ph.img.susercontent.com/file/a27d594cd31c08567759f065aae2adc3_tn",
        "price": "₱289 - ₱1,090",
        "location": "Guiguinto, Bulacan",
        "sold_items": "6.4K sold",
        "category": "appliances"
    },
    {
        "id": 598,
        "name": "READY STOCK 40x40 45x45 50x50 55x55 30x50 cm Large Linen Plain Cushion Cover Throw Pillow Case Home Sofa Decor",
        "img": "https://down-ph.img.susercontent.com/file/6986a0b6b5822bb62a58f76297d9c701_tn",
        "price": "₱139 - ₱186",
        "location": "Mainland China",
        "sold_items": "10K+ sold",
        "category": "appliances"
    },
    {
        "id": 599,
        "name": "Automatic Roller Washer Cover Waterproof Dustproof Washing Machine Cover front load Automatic drum",
        "img": "https://down-ph.img.susercontent.com/file/0fcf76c7b0a3207b68d224191695b6d5_tn",
        "price": "₱269 - ₱279",
        "location": "Caloocan City, Metro Manila",
        "sold_items": "3.2K sold",
        "category": "appliances"
    },
    {
        "id": 600,
        "name": "【PH STOCK & COD] 1/2/3 Seater Sofa Cover Set Elastic Universal Armless Regular Shape L Shape",
        "img": "https://down-ph.img.susercontent.com/file/ph-11134201-23030-mu1ugtrbywov79_tn",
        "price": "₱69 - ₱339",
        "location": "Caloocan City, Metro Manila",
        "sold_items": "4.3K sold",
        "category": "appliances"
    }
]